iotile/__init__.py
iotile/ship/__init__.py
iotile/ship/exceptions.py
iotile/ship/recipe.py
iotile/ship/recipe_format.py
iotile/ship/recipe_manager.py
iotile/ship/actions/ModifyJsonStep.py
iotile/ship/actions/__init__.py
iotile/ship/actions/pipe_snippet_step.py
iotile/ship/actions/prompt_step.py
iotile/ship/actions/send_ota_script_step.py
iotile/ship/actions/sync_cloud_step.py
iotile/ship/actions/sync_rtc_step.py
iotile/ship/actions/verify_device_step.py
iotile/ship/actions/wait_step.py
iotile/ship/autobuild/__init__.py
iotile/ship/autobuild/ship_file.py
iotile/ship/resources/__init__.py
iotile/ship/resources/filesystem_manager.py
iotile/ship/resources/hardware_manager.py
iotile/ship/resources/shared_resource.py
iotile/ship/scripts/__init__.py
iotile/ship/scripts/iotile_ship.py
iotile_ship-1.1.0.dist-info/LICENSE.md
iotile_ship-1.1.0.dist-info/METADATA
iotile_ship-1.1.0.dist-info/WHEEL
iotile_ship-1.1.0.dist-info/entry_points.txt
iotile_ship-1.1.0.dist-info/top_level.txt
iotile_ship-1.1.0.dist-info/RECORD
